{
    "versions": [
        {
            "version": "1.5.0",
            "date": "2025-12-08",
            "type": "minor",
            "title": "Smart Templates & Integration Update",
            "changes": [
                {
                    "type": "feat",
                    "text": "Smart Templates View: Dedicated overview for starting new projects with specialized templates."
                },
                {
                    "type": "feat",
                    "text": "Task Tool Integrations: Restored 'Open Suno', 'Copy Prompt', etc., directly within tasks."
                },
                {
                    "type": "feat",
                    "text": "File Drop Zone: Drag-and-drop file upload in Project Assets with auto-task completion."
                },
                {
                    "type": "feat",
                    "text": "Smart Prompts: AI-powered prompt generator for Suno, Cover Art, Stories, and more."
                },
                {
                    "type": "fix",
                    "text": "Local Media Display: Resolved 'Not allowed to load local resource' errors using secure media:// protocol."
                },
                {
                    "type": "feat",
                    "text": "Project Management Hook: Enhanced state management for projects and statistics."
                }
            ]
        },
        {
            "version": "1.1.0",
            "date": "2025-12-02",
            "type": "minor",
            "title": "Desktop Integration & Smart Scanning",
            "changes": [
                {
                    "type": "feat",
                    "text": "Electron-Integration für Desktop-Nutzung"
                },
                {
                    "type": "feat",
                    "text": "Intelligenter Projekt-Scan (Album, Song, Commercial) in C:\\Downloads"
                },
                {
                    "type": "feat",
                    "text": "Automatische Erkennung von Projekt-Strukturen und Track-Anzahl"
                },
                {
                    "type": "feat",
                    "text": "Erweitertes Error-Logging System"
                },
                {
                    "type": "docs",
                    "text": "Benutzer-Dokumentation aktualisiert"
                }
            ]
        },
        {
            "version": "1.0.1",
            "date": "2025-12-02",
            "type": "patch",
            "title": "Bugfixes & Lokalisierung",
            "changes": [
                {
                    "type": "fix",
                    "text": "Korrektur der CSS-Layout-Probleme im Dashboard"
                },
                {
                    "type": "fix",
                    "text": "Behebung von Syntax-Fehlern in Komponenten"
                },
                {
                    "type": "feat",
                    "text": "Vollständige deutsche Lokalisierung"
                },
                {
                    "type": "ui",
                    "text": "Dark Mode und Glassmorphismus Design-Update"
                }
            ]
        },
        {
            "version": "1.0.0",
            "date": "2025-12-01",
            "type": "major",
            "title": "Initial Release",
            "changes": [
                {
                    "type": "feat",
                    "text": "Basis-Funktionalität: Projekt-Erstellung und Verwaltung"
                },
                {
                    "type": "feat",
                    "text": "Fortschritts-Tracking und Statistiken"
                }
            ]
        }
    ]
}